naturtag/__init__.py
naturtag/cli.py
naturtag/constants.py
naturtag/py.typed
naturtag/app/__init__.py
naturtag/app/app.py
naturtag/app/controls.py
naturtag/app/settings_menu.py
naturtag/app/threadpool.py
naturtag/controllers/__init__.py
naturtag/controllers/base_controller.py
naturtag/controllers/image_controller.py
naturtag/controllers/image_gallery.py
naturtag/controllers/observation_controller.py
naturtag/controllers/observation_search.py
naturtag/controllers/observation_view.py
naturtag/controllers/taxon_controller.py
naturtag/controllers/taxon_search.py
naturtag/controllers/taxon_view.py
naturtag/metadata/__init__.py
naturtag/metadata/gps_metadata.py
naturtag/metadata/image_metadata.py
naturtag/metadata/inat_metadata.py
naturtag/metadata/keyword_metadata.py
naturtag/metadata/meta_metadata.py
naturtag/storage/__init__.py
naturtag/storage/app_state.py
naturtag/storage/client.py
naturtag/storage/session.py
naturtag/storage/settings.py
naturtag/storage/setup.py
naturtag/utils/__init__.py
naturtag/utils/i18n.py
naturtag/utils/image_glob.py
naturtag/utils/parsing.py
naturtag/utils/thumbnails.py
naturtag/widgets/__init__.py
naturtag/widgets/autocomplete.py
naturtag/widgets/images.py
naturtag/widgets/inputs.py
naturtag/widgets/layouts.py
naturtag/widgets/logger.py
naturtag/widgets/observation_images.py
naturtag/widgets/style.py
naturtag/widgets/taxon_images.py
naturtag/widgets/toggle_switch.py
naturtag-0.8.2.dist-info/METADATA
naturtag-0.8.2.dist-info/WHEEL
naturtag-0.8.2.dist-info/entry_points.txt
naturtag-0.8.2.dist-info/licenses/LICENSE
naturtag-0.8.2.dist-info/RECORD
