Metadata-Version: 2.4
Name: naturtag
Version: 0.8.2
Summary: Tag your nature photos with iNat taxonomy and observation metadata
Project-URL: Homepage, https://github.com/pyinat/naturtag
Project-URL: Repository, https://github.com/pyinat/naturtag
Project-URL: Documentation, https://naturtag.readthedocs.io
Author: Jordan Cook
License: MIT
License-File: LICENSE
Classifier: Development Status :: 3 - Alpha
Classifier: Environment :: Console
Classifier: Environment :: MacOS X
Classifier: Environment :: Win32 (MS Windows)
Classifier: Environment :: X11 Applications
Classifier: Intended Audience :: Developers
Classifier: Intended Audience :: End Users/Desktop
Classifier: Intended Audience :: Science/Research
Classifier: Operating System :: MacOS
Classifier: Operating System :: Microsoft :: Windows
Classifier: Operating System :: POSIX
Classifier: Typing :: Typed
Requires-Python: <3.15,>=3.14
Requires-Dist: attrs>=21.2
Requires-Dist: click-help-colors>=0.9
Requires-Dist: click>=8.0
Requires-Dist: pillow>=10.0
Requires-Dist: pyexiv2>=2.10
Requires-Dist: pyinaturalist-convert>=0.7.1
Requires-Dist: pyinaturalist>=0.20
Requires-Dist: pyqtdarktheme-fork~=2.3.4
Requires-Dist: pyside6==6.10.1
Requires-Dist: pyyaml>=6.0
Requires-Dist: qtawesome~=1.4.0
Requires-Dist: sqlalchemy~=2.0.45
Requires-Dist: tablib~=3.9
Provides-Extra: docs
Requires-Dist: furo~=2025.12.19; extra == 'docs'
Requires-Dist: linkify-it-py>=2.0; extra == 'docs'
Requires-Dist: myst-parser~=4.0; extra == 'docs'
Requires-Dist: sphinx-autodoc-typehints~=3.5; extra == 'docs'
Requires-Dist: sphinx-copybutton>=0.5; extra == 'docs'
Requires-Dist: sphinx-design>=0.2; extra == 'docs'
Requires-Dist: sphinxcontrib-apidoc>=0.6; extra == 'docs'
Requires-Dist: sphinx~=8.2; extra == 'docs'
